pelican/plugins/timegraphics/__init__.py
pelican/plugins/timegraphics/test_timegraphics.py
pelican/plugins/timegraphics/timegraphics.py
pelican_timegraphics_plugin-1.0.1.dist-info/WHEEL
pelican_timegraphics_plugin-1.0.1.dist-info/METADATA
pelican_timegraphics_plugin-1.0.1.dist-info/RECORD
