Metadata-Version: 2.1
Name: pelican-timegraphics-plugin
Version: 1.0.1
Summary: Easily embed Time.Graphics timelines in your Pelican articles
Home-page: https://github.com/johanvergeer/pelican-timegraphics-plugin
License: MIT
Keywords: pelican,plugin,timegraphics
Author: Johan Vergeer
Author-email: johanvergeer@gmail.com
Requires-Python: >=3.6,<4.0
Classifier: Development Status :: 5 - Production/Stable
Classifier: Environment :: Console
Classifier: Framework :: Pelican
Classifier: Framework :: Pelican :: Plugins
Classifier: Intended Audience :: End Users/Desktop
Classifier: License :: OSI Approved :: MIT License
Classifier: Operating System :: OS Independent
Classifier: Programming Language :: Python
Classifier: Programming Language :: Python :: 3
Classifier: Programming Language :: Python :: 3.6
Classifier: Programming Language :: Python :: 3.7
Classifier: Programming Language :: Python :: 3.8
Classifier: Topic :: Internet :: WWW/HTTP
Classifier: Topic :: Software Development :: Libraries :: Python Modules
Provides-Extra: markdown
Requires-Dist: markdown (>=3.1.1,<4.0.0); extra == "markdown"
Requires-Dist: pelican (>=4.2,<5.0)
Project-URL: Documentation, https://docs.getpelican.com/
Project-URL: Funding, https://donate.getpelican.com/
Project-URL: Repository, https://github.com/johanvergeer/pelican-timegraphics-plugin
Project-URL: Source, https://github.com/johanvergeer/pelican-timegraphics-plugin
Project-URL: Tracker, https://github.com/johanvergeer/pelican-timegraphics-plugin/issues
